LICENSE
MANIFEST.in
README.rst
RELEASE.md
setup.py
pyopendata/__init__.py
pyopendata/base.py
pyopendata/ckan.py
pyopendata/eurostat.py
pyopendata/oecd.py
pyopendata/undata.py
pyopendata/version.py
pyopendata/worldbank.py
pyopendata.egg-info/PKG-INFO
pyopendata.egg-info/SOURCES.txt
pyopendata.egg-info/dependency_links.txt
pyopendata.egg-info/requires.txt
pyopendata.egg-info/top_level.txt
pyopendata/io/__init__.py
pyopendata/io/jsdmx.py
pyopendata/io/jstat.py
pyopendata/io/sdmx.py
pyopendata/io/util.py
pyopendata/io/tests/__init__.py
pyopendata/io/tests/test_jsdmx.py
pyopendata/io/tests/test_jstat.py
pyopendata/io/tests/test_sdmx.py
pyopendata/tests/__init__.py
pyopendata/tests/test_base.py
pyopendata/tests/test_ckan.py
pyopendata/tests/test_eurostat.py
pyopendata/tests/test_oecd.py
pyopendata/tests/test_worldbank.py
pyopendata/util/__init__.py
pyopendata/util/network.py