Metadata-Version: 1.0
Name: pyopendata
Version: 0.0.2
Summary: Python utility to get open data from some popular websites
Home-page: http://pyopendata.readthedocs.org
Author: sinhrks
Author-email: sinhrks@gmail.com
License: BSD
Platform: UNKNOWN
